europeana
