Metadata-Version: 1.1
Name: django-europeana
Version: 0.1.5
Summary: Application providing Europeana widget integration.
Home-page: http://www.aksprendimai.lt/
Author: Justinas Jaronis, Inga Pliavgo, Ignas Bacius, Mykolas Baranauskas
Author-email: info@aksprendimai.lt
License: GNU Affero General Public License v3 or later (AGPLv3+)
Platform: UNKNOWN
Classifier: Environment :: Web Environment
Classifier: Framework :: Django
Classifier: Intended Audience :: Developers
Classifier: License :: OSI Approved :: GNU Affero General Public License v3 or later (AGPLv3+)
Classifier: Operating System :: OS Independent
Classifier: Programming Language :: Python
Classifier: Programming Language :: Python :: 2.6
Classifier: Programming Language :: Python :: 2.7
Classifier: Topic :: Internet :: WWW/HTTP
Classifier: Topic :: Internet :: WWW/HTTP :: Dynamic Content
